odoo10_addon_account_fiscal_position_rule_sale_stock-10.0.1.0.0.99.dev5-py3.8-nspkg.pth
odoo/addons/account_fiscal_position_rule_sale_stock/README.rst
odoo/addons/account_fiscal_position_rule_sale_stock/__init__.py
odoo/addons/account_fiscal_position_rule_sale_stock/__manifest__.py
odoo/addons/account_fiscal_position_rule_sale_stock/i18n/account_fiscal_position_rule_sale_stock.pot
odoo/addons/account_fiscal_position_rule_sale_stock/i18n/pt_BR.po
odoo/addons/account_fiscal_position_rule_sale_stock/models/__init__.py
odoo/addons/account_fiscal_position_rule_sale_stock/models/stock_picking.py
odoo/addons/account_fiscal_position_rule_sale_stock/readme/CONFIGURE.rst
odoo/addons/account_fiscal_position_rule_sale_stock/readme/CONTRIBUTORS.rst
odoo/addons/account_fiscal_position_rule_sale_stock/readme/CREDITS.rst
odoo/addons/account_fiscal_position_rule_sale_stock/readme/DESCRIPTION.rst
odoo/addons/account_fiscal_position_rule_sale_stock/readme/HISTORY.rst
odoo/addons/account_fiscal_position_rule_sale_stock/readme/INSTALL.rst
odoo/addons/account_fiscal_position_rule_sale_stock/readme/ROADMAP.rst
odoo/addons/account_fiscal_position_rule_sale_stock/readme/USAGE.rst
odoo/addons/account_fiscal_position_rule_sale_stock/security/ir.model.access.csv
odoo/addons/account_fiscal_position_rule_sale_stock/static/description/icon.png
odoo/addons/account_fiscal_position_rule_sale_stock/static/description/index.html
odoo/addons/account_fiscal_position_rule_sale_stock/tests/__init__.py
odoo/addons/account_fiscal_position_rule_sale_stock/tests/test_account_fiscal_position_rule_sale_stock.py
odoo10_addon_account_fiscal_position_rule_sale_stock-10.0.1.0.0.99.dev5.dist-info/METADATA
odoo10_addon_account_fiscal_position_rule_sale_stock-10.0.1.0.0.99.dev5.dist-info/WHEEL
odoo10_addon_account_fiscal_position_rule_sale_stock-10.0.1.0.0.99.dev5.dist-info/namespace_packages.txt
odoo10_addon_account_fiscal_position_rule_sale_stock-10.0.1.0.0.99.dev5.dist-info/top_level.txt
odoo10_addon_account_fiscal_position_rule_sale_stock-10.0.1.0.0.99.dev5.dist-info/RECORD
